<?xml version="1.0" encoding="UTF-8" standalone="yes"?>
<template encoding-version="1.3">
    <description></description>
    <groupId>6c6e81a6-0183-1000-862c-c3875bd6dbf4</groupId>
    <name>masterClass</name>
    <snippet>
        <processGroups>
            <id>660ff45f-c676-36f7-0000-000000000000</id>
            <parentGroupId>584d314a-58b4-3a4d-0000-000000000000</parentGroupId>
            <position>
                <x>0.0</x>
                <y>0.0</y>
            </position>
            <comments></comments>
            <contents>
                <connections>
                    <id>2957a4fd-3c94-39d3-0000-000000000000</id>
                    <parentGroupId>660ff45f-c676-36f7-0000-000000000000</parentGroupId>
                    <backPressureDataSizeThreshold>1 GB</backPressureDataSizeThreshold>
                    <backPressureObjectThreshold>10000</backPressureObjectThreshold>
                    <destination>
                        <groupId>660ff45f-c676-36f7-0000-000000000000</groupId>
                        <id>234e89a7-7385-3268-0000-000000000000</id>
                        <type>PROCESSOR</type>
                    </destination>
                    <flowFileExpiration>0 sec</flowFileExpiration>
                    <labelIndex>1</labelIndex>
                    <loadBalanceCompression>DO_NOT_COMPRESS</loadBalanceCompression>
                    <loadBalancePartitionAttribute></loadBalancePartitionAttribute>
                    <loadBalanceStatus>LOAD_BALANCE_NOT_CONFIGURED</loadBalanceStatus>
                    <loadBalanceStrategy>DO_NOT_LOAD_BALANCE</loadBalanceStrategy>
                    <name></name>
                    <selectedRelationships>success</selectedRelationships>
                    <source>
                        <groupId>660ff45f-c676-36f7-0000-000000000000</groupId>
                        <id>86a4e143-ff9f-3d6b-0000-000000000000</id>
                        <type>PROCESSOR</type>
                    </source>
                    <zIndex>0</zIndex>
                </connections>
                <connections>
                    <id>6f987eee-faa3-39e5-0000-000000000000</id>
                    <parentGroupId>660ff45f-c676-36f7-0000-000000000000</parentGroupId>
                    <backPressureDataSizeThreshold>1 GB</backPressureDataSizeThreshold>
                    <backPressureObjectThreshold>10000</backPressureObjectThreshold>
                    <destination>
                        <groupId>660ff45f-c676-36f7-0000-000000000000</groupId>
                        <id>f6f4ea60-3417-3c87-0000-000000000000</id>
                        <type>PROCESSOR</type>
                    </destination>
                    <flowFileExpiration>0 sec</flowFileExpiration>
                    <labelIndex>1</labelIndex>
                    <loadBalanceCompression>DO_NOT_COMPRESS</loadBalanceCompression>
                    <loadBalancePartitionAttribute></loadBalancePartitionAttribute>
                    <loadBalanceStatus>LOAD_BALANCE_NOT_CONFIGURED</loadBalanceStatus>
                    <loadBalanceStrategy>DO_NOT_LOAD_BALANCE</loadBalanceStrategy>
                    <name></name>
                    <selectedRelationships>success</selectedRelationships>
                    <source>
                        <groupId>660ff45f-c676-36f7-0000-000000000000</groupId>
                        <id>ad8dd498-ece0-3d6f-0000-000000000000</id>
                        <type>PROCESSOR</type>
                    </source>
                    <zIndex>0</zIndex>
                </connections>
                <connections>
                    <id>b0a699c5-4856-3db3-0000-000000000000</id>
                    <parentGroupId>660ff45f-c676-36f7-0000-000000000000</parentGroupId>
                    <backPressureDataSizeThreshold>1 GB</backPressureDataSizeThreshold>
                    <backPressureObjectThreshold>10000</backPressureObjectThreshold>
                    <destination>
                        <groupId>660ff45f-c676-36f7-0000-000000000000</groupId>
                        <id>4fec4974-bfb9-3e38-0000-000000000000</id>
                        <type>OUTPUT_PORT</type>
                    </destination>
                    <flowFileExpiration>0 sec</flowFileExpiration>
                    <labelIndex>1</labelIndex>
                    <loadBalanceCompression>DO_NOT_COMPRESS</loadBalanceCompression>
                    <loadBalancePartitionAttribute></loadBalancePartitionAttribute>
                    <loadBalanceStatus>LOAD_BALANCE_NOT_CONFIGURED</loadBalanceStatus>
                    <loadBalanceStrategy>DO_NOT_LOAD_BALANCE</loadBalanceStrategy>
                    <name></name>
                    <selectedRelationships>output stream</selectedRelationships>
                    <source>
                        <groupId>660ff45f-c676-36f7-0000-000000000000</groupId>
                        <id>234e89a7-7385-3268-0000-000000000000</id>
                        <type>PROCESSOR</type>
                    </source>
                    <zIndex>0</zIndex>
                </connections>
                <connections>
                    <id>c22eda0e-ca3c-35f6-0000-000000000000</id>
                    <parentGroupId>660ff45f-c676-36f7-0000-000000000000</parentGroupId>
                    <backPressureDataSizeThreshold>1 GB</backPressureDataSizeThreshold>
                    <backPressureObjectThreshold>10000</backPressureObjectThreshold>
                    <destination>
                        <groupId>660ff45f-c676-36f7-0000-000000000000</groupId>
                        <id>4fec4974-bfb9-3e38-0000-000000000000</id>
                        <type>OUTPUT_PORT</type>
                    </destination>
                    <flowFileExpiration>0 sec</flowFileExpiration>
                    <labelIndex>1</labelIndex>
                    <loadBalanceCompression>DO_NOT_COMPRESS</loadBalanceCompression>
                    <loadBalancePartitionAttribute></loadBalancePartitionAttribute>
                    <loadBalanceStatus>LOAD_BALANCE_NOT_CONFIGURED</loadBalanceStatus>
                    <loadBalanceStrategy>DO_NOT_LOAD_BALANCE</loadBalanceStrategy>
                    <name></name>
                    <selectedRelationships>success</selectedRelationships>
                    <source>
                        <groupId>660ff45f-c676-36f7-0000-000000000000</groupId>
                        <id>f6f4ea60-3417-3c87-0000-000000000000</id>
                        <type>PROCESSOR</type>
                    </source>
                    <zIndex>0</zIndex>
                </connections>
                <outputPorts>
                    <id>4fec4974-bfb9-3e38-0000-000000000000</id>
                    <parentGroupId>660ff45f-c676-36f7-0000-000000000000</parentGroupId>
                    <position>
                        <x>432.0</x>
                        <y>624.0</y>
                    </position>
                    <allowRemoteAccess>true</allowRemoteAccess>
                    <comments></comments>
                    <concurrentlySchedulableTaskCount>1</concurrentlySchedulableTaskCount>
                    <name>end</name>
                    <state>STOPPED</state>
                    <transmitting>false</transmitting>
                    <type>OUTPUT_PORT</type>
                </outputPorts>
                <processors>
                    <id>234e89a7-7385-3268-0000-000000000000</id>
                    <parentGroupId>660ff45f-c676-36f7-0000-000000000000</parentGroupId>
                    <position>
                        <x>136.0</x>
                        <y>304.0</y>
                    </position>
                    <bundle>
                        <artifact>nifi-standard-nar</artifact>
                        <group>org.apache.nifi</group>
                        <version>1.15.2</version>
                    </bundle>
                    <config>
                        <bulletinLevel>WARN</bulletinLevel>
                        <comments></comments>
                        <concurrentlySchedulableTaskCount>1</concurrentlySchedulableTaskCount>
                        <descriptors>
                            <entry>
<key>argumentsStrategy</key>
<value>
    <name>argumentsStrategy</name>
</value>
                            </entry>
                            <entry>
<key>Command Arguments</key>
<value>
    <name>Command Arguments</name>
</value>
                            </entry>
                            <entry>
<key>Command Path</key>
<value>
    <name>Command Path</name>
</value>
                            </entry>
                            <entry>
<key>Ignore STDIN</key>
<value>
    <name>Ignore STDIN</name>
</value>
                            </entry>
                            <entry>
<key>Working Directory</key>
<value>
    <name>Working Directory</name>
</value>
                            </entry>
                            <entry>
<key>Argument Delimiter</key>
<value>
    <name>Argument Delimiter</name>
</value>
                            </entry>
                            <entry>
<key>Output Destination Attribute</key>
<value>
    <name>Output Destination Attribute</name>
</value>
                            </entry>
                            <entry>
<key>Max Attribute Length</key>
<value>
    <name>Max Attribute Length</name>
</value>
                            </entry>
                        </descriptors>
                        <executionNode>ALL</executionNode>
                        <lossTolerant>false</lossTolerant>
                        <penaltyDuration>30 sec</penaltyDuration>
                        <properties>
                            <entry>
<key>argumentsStrategy</key>
<value>Command Arguments Property</value>
                            </entry>
                            <entry>
<key>Command Arguments</key>
                            </entry>
                            <entry>
<key>Command Path</key>
<value>/opt/nifi_conf/scrappermasterclass.sh</value>
                            </entry>
                            <entry>
<key>Ignore STDIN</key>
<value>false</value>
                            </entry>
                            <entry>
<key>Working Directory</key>
                            </entry>
                            <entry>
<key>Argument Delimiter</key>
<value>;</value>
                            </entry>
                            <entry>
<key>Output Destination Attribute</key>
                            </entry>
                            <entry>
<key>Max Attribute Length</key>
<value>256</value>
                            </entry>
                        </properties>
                        <runDurationMillis>0</runDurationMillis>
                        <schedulingPeriod>0 sec</schedulingPeriod>
                        <schedulingStrategy>TIMER_DRIVEN</schedulingStrategy>
                        <yieldDuration>1 sec</yieldDuration>
                    </config>
                    <executionNodeRestricted>false</executionNodeRestricted>
                    <name>ejecutaScrapper</name>
                    <relationships>
                        <autoTerminate>true</autoTerminate>
                        <name>nonzero status</name>
                    </relationships>
                    <relationships>
                        <autoTerminate>true</autoTerminate>
                        <name>original</name>
                    </relationships>
                    <relationships>
                        <autoTerminate>false</autoTerminate>
                        <name>output stream</name>
                    </relationships>
                    <state>RUNNING</state>
                    <style/>
                    <type>org.apache.nifi.processors.standard.ExecuteStreamCommand</type>
                </processors>
                <processors>
                    <id>86a4e143-ff9f-3d6b-0000-000000000000</id>
                    <parentGroupId>660ff45f-c676-36f7-0000-000000000000</parentGroupId>
                    <position>
                        <x>136.0</x>
                        <y>16.0</y>
                    </position>
                    <bundle>
                        <artifact>nifi-standard-nar</artifact>
                        <group>org.apache.nifi</group>
                        <version>1.15.2</version>
                    </bundle>
                    <config>
                        <bulletinLevel>WARN</bulletinLevel>
                        <comments></comments>
                        <concurrentlySchedulableTaskCount>1</concurrentlySchedulableTaskCount>
                        <descriptors>
                            <entry>
<key>Base Path</key>
<value>
    <name>Base Path</name>
</value>
                            </entry>
                            <entry>
<key>Listening Port</key>
<value>
    <name>Listening Port</name>
</value>
                            </entry>
                            <entry>
<key>health-check-port</key>
<value>
    <name>health-check-port</name>
</value>
                            </entry>
                            <entry>
<key>Max Data to Receive per Second</key>
<value>
    <name>Max Data to Receive per Second</name>
</value>
                            </entry>
                            <entry>
<key>SSL Context Service</key>
<value>
    <identifiesControllerService>org.apache.nifi.ssl.RestrictedSSLContextService</identifiesControllerService>
    <name>SSL Context Service</name>
</value>
                            </entry>
                            <entry>
<key>client-authentication</key>
<value>
    <dependencies>
        <propertyName>SSL Context Service</propertyName>
    </dependencies>
    <name>client-authentication</name>
</value>
                            </entry>
                            <entry>
<key>Authorized DN Pattern</key>
<value>
    <name>Authorized DN Pattern</name>
</value>
                            </entry>
                            <entry>
<key>authorized-issuer-dn-pattern</key>
<value>
    <name>authorized-issuer-dn-pattern</name>
</value>
                            </entry>
                            <entry>
<key>Max Unconfirmed Flowfile Time</key>
<value>
    <name>Max Unconfirmed Flowfile Time</name>
</value>
                            </entry>
                            <entry>
<key>HTTP Headers to receive as Attributes (Regex)</key>
<value>
    <name>HTTP Headers to receive as Attributes (Regex)</name>
</value>
                            </entry>
                            <entry>
<key>Return Code</key>
<value>
    <name>Return Code</name>
</value>
                            </entry>
                            <entry>
<key>multipart-request-max-size</key>
<value>
    <name>multipart-request-max-size</name>
</value>
                            </entry>
                            <entry>
<key>multipart-read-buffer-size</key>
<value>
    <name>multipart-read-buffer-size</name>
</value>
                            </entry>
                            <entry>
<key>max-thread-pool-size</key>
<value>
    <name>max-thread-pool-size</name>
</value>
                            </entry>
                            <entry>
<key>record-reader</key>
<value>
    <identifiesControllerService>org.apache.nifi.serialization.RecordReaderFactory</identifiesControllerService>
    <name>record-reader</name>
</value>
                            </entry>
                            <entry>
<key>record-writer</key>
<value>
    <dependencies>
        <propertyName>record-reader</propertyName>
    </dependencies>
    <identifiesControllerService>org.apache.nifi.serialization.RecordSetWriterFactory</identifiesControllerService>
    <name>record-writer</name>
</value>
                            </entry>
                        </descriptors>
                        <executionNode>ALL</executionNode>
                        <lossTolerant>false</lossTolerant>
                        <penaltyDuration>30 sec</penaltyDuration>
                        <properties>
                            <entry>
<key>Base Path</key>
<value>scrapper</value>
                            </entry>
                            <entry>
<key>Listening Port</key>
<value>5000</value>
                            </entry>
                            <entry>
<key>health-check-port</key>
                            </entry>
                            <entry>
<key>Max Data to Receive per Second</key>
                            </entry>
                            <entry>
<key>SSL Context Service</key>
                            </entry>
                            <entry>
<key>client-authentication</key>
<value>AUTO</value>
                            </entry>
                            <entry>
<key>Authorized DN Pattern</key>
<value>.*</value>
                            </entry>
                            <entry>
<key>authorized-issuer-dn-pattern</key>
<value>.*</value>
                            </entry>
                            <entry>
<key>Max Unconfirmed Flowfile Time</key>
<value>60 secs</value>
                            </entry>
                            <entry>
<key>HTTP Headers to receive as Attributes (Regex)</key>
                            </entry>
                            <entry>
<key>Return Code</key>
<value>200</value>
                            </entry>
                            <entry>
<key>multipart-request-max-size</key>
<value>1 MB</value>
                            </entry>
                            <entry>
<key>multipart-read-buffer-size</key>
<value>512 KB</value>
                            </entry>
                            <entry>
<key>max-thread-pool-size</key>
<value>200</value>
                            </entry>
                            <entry>
<key>record-reader</key>
                            </entry>
                            <entry>
<key>record-writer</key>
                            </entry>
                        </properties>
                        <runDurationMillis>0</runDurationMillis>
                        <schedulingPeriod>0 sec</schedulingPeriod>
                        <schedulingStrategy>TIMER_DRIVEN</schedulingStrategy>
                        <yieldDuration>1 sec</yieldDuration>
                    </config>
                    <executionNodeRestricted>false</executionNodeRestricted>
                    <name>disparadorScrapper</name>
                    <relationships>
                        <autoTerminate>false</autoTerminate>
                        <name>success</name>
                    </relationships>
                    <state>RUNNING</state>
                    <style/>
                    <type>org.apache.nifi.processors.standard.ListenHTTP</type>
                </processors>
                <processors>
                    <id>ad8dd498-ece0-3d6f-0000-000000000000</id>
                    <parentGroupId>660ff45f-c676-36f7-0000-000000000000</parentGroupId>
                    <position>
                        <x>728.0</x>
                        <y>8.0</y>
                    </position>
                    <bundle>
                        <artifact>nifi-standard-nar</artifact>
                        <group>org.apache.nifi</group>
                        <version>1.15.2</version>
                    </bundle>
                    <config>
                        <bulletinLevel>WARN</bulletinLevel>
                        <comments></comments>
                        <concurrentlySchedulableTaskCount>1</concurrentlySchedulableTaskCount>
                        <descriptors>
                            <entry>
<key>Input Directory</key>
<value>
    <name>Input Directory</name>
</value>
                            </entry>
                            <entry>
<key>File Filter</key>
<value>
    <name>File Filter</name>
</value>
                            </entry>
                            <entry>
<key>Path Filter</key>
<value>
    <name>Path Filter</name>
</value>
                            </entry>
                            <entry>
<key>Batch Size</key>
<value>
    <name>Batch Size</name>
</value>
                            </entry>
                            <entry>
<key>Keep Source File</key>
<value>
    <name>Keep Source File</name>
</value>
                            </entry>
                            <entry>
<key>Recurse Subdirectories</key>
<value>
    <name>Recurse Subdirectories</name>
</value>
                            </entry>
                            <entry>
<key>Polling Interval</key>
<value>
    <name>Polling Interval</name>
</value>
                            </entry>
                            <entry>
<key>Ignore Hidden Files</key>
<value>
    <name>Ignore Hidden Files</name>
</value>
                            </entry>
                            <entry>
<key>Minimum File Age</key>
<value>
    <name>Minimum File Age</name>
</value>
                            </entry>
                            <entry>
<key>Maximum File Age</key>
<value>
    <name>Maximum File Age</name>
</value>
                            </entry>
                            <entry>
<key>Minimum File Size</key>
<value>
    <name>Minimum File Size</name>
</value>
                            </entry>
                            <entry>
<key>Maximum File Size</key>
<value>
    <name>Maximum File Size</name>
</value>
                            </entry>
                        </descriptors>
                        <executionNode>ALL</executionNode>
                        <lossTolerant>false</lossTolerant>
                        <penaltyDuration>30 sec</penaltyDuration>
                        <properties>
                            <entry>
<key>Input Directory</key>
<value>/opt/nifi_conf</value>
                            </entry>
                            <entry>
<key>File Filter</key>
<value>(.*?).csv</value>
                            </entry>
                            <entry>
<key>Path Filter</key>
                            </entry>
                            <entry>
<key>Batch Size</key>
<value>10</value>
                            </entry>
                            <entry>
<key>Keep Source File</key>
<value>false</value>
                            </entry>
                            <entry>
<key>Recurse Subdirectories</key>
<value>false</value>
                            </entry>
                            <entry>
<key>Polling Interval</key>
<value>0 sec</value>
                            </entry>
                            <entry>
<key>Ignore Hidden Files</key>
<value>true</value>
                            </entry>
                            <entry>
<key>Minimum File Age</key>
<value>0 sec</value>
                            </entry>
                            <entry>
<key>Maximum File Age</key>
                            </entry>
                            <entry>
<key>Minimum File Size</key>
<value>0 B</value>
                            </entry>
                            <entry>
<key>Maximum File Size</key>
                            </entry>
                        </properties>
                        <runDurationMillis>0</runDurationMillis>
                        <schedulingPeriod>0 sec</schedulingPeriod>
                        <schedulingStrategy>TIMER_DRIVEN</schedulingStrategy>
                        <yieldDuration>1 sec</yieldDuration>
                    </config>
                    <executionNodeRestricted>false</executionNodeRestricted>
                    <name>obtenerCsv</name>
                    <relationships>
                        <autoTerminate>false</autoTerminate>
                        <name>success</name>
                    </relationships>
                    <state>RUNNING</state>
                    <style/>
                    <type>org.apache.nifi.processors.standard.GetFile</type>
                </processors>
                <processors>
                    <id>f6f4ea60-3417-3c87-0000-000000000000</id>
                    <parentGroupId>660ff45f-c676-36f7-0000-000000000000</parentGroupId>
                    <position>
                        <x>728.0</x>
                        <y>320.0</y>
                    </position>
                    <bundle>
                        <artifact>nifi-hadoop-nar</artifact>
                        <group>org.apache.nifi</group>
                        <version>1.15.2</version>
                    </bundle>
                    <config>
                        <bulletinLevel>WARN</bulletinLevel>
                        <comments></comments>
                        <concurrentlySchedulableTaskCount>1</concurrentlySchedulableTaskCount>
                        <descriptors>
                            <entry>
<key>Hadoop Configuration Resources</key>
<value>
    <name>Hadoop Configuration Resources</name>
</value>
                            </entry>
                            <entry>
<key>kerberos-credentials-service</key>
<value>
    <identifiesControllerService>org.apache.nifi.kerberos.KerberosCredentialsService</identifiesControllerService>
    <name>kerberos-credentials-service</name>
</value>
                            </entry>
                            <entry>
<key>kerberos-user-service</key>
<value>
    <identifiesControllerService>org.apache.nifi.kerberos.KerberosUserService</identifiesControllerService>
    <name>kerberos-user-service</name>
</value>
                            </entry>
                            <entry>
<key>Kerberos Principal</key>
<value>
    <name>Kerberos Principal</name>
</value>
                            </entry>
                            <entry>
<key>Kerberos Keytab</key>
<value>
    <name>Kerberos Keytab</name>
</value>
                            </entry>
                            <entry>
<key>Kerberos Password</key>
<value>
    <name>Kerberos Password</name>
</value>
                            </entry>
                            <entry>
<key>Kerberos Relogin Period</key>
<value>
    <name>Kerberos Relogin Period</name>
</value>
                            </entry>
                            <entry>
<key>Additional Classpath Resources</key>
<value>
    <name>Additional Classpath Resources</name>
</value>
                            </entry>
                            <entry>
<key>Directory</key>
<value>
    <name>Directory</name>
</value>
                            </entry>
                            <entry>
<key>Conflict Resolution Strategy</key>
<value>
    <name>Conflict Resolution Strategy</name>
</value>
                            </entry>
                            <entry>
<key>writing-strategy</key>
<value>
    <name>writing-strategy</name>
</value>
                            </entry>
                            <entry>
<key>Block Size</key>
<value>
    <name>Block Size</name>
</value>
                            </entry>
                            <entry>
<key>IO Buffer Size</key>
<value>
    <name>IO Buffer Size</name>
</value>
                            </entry>
                            <entry>
<key>Replication</key>
<value>
    <name>Replication</name>
</value>
                            </entry>
                            <entry>
<key>Permissions umask</key>
<value>
    <name>Permissions umask</name>
</value>
                            </entry>
                            <entry>
<key>Remote Owner</key>
<value>
    <name>Remote Owner</name>
</value>
                            </entry>
                            <entry>
<key>Remote Group</key>
<value>
    <name>Remote Group</name>
</value>
                            </entry>
                            <entry>
<key>Compression codec</key>
<value>
    <name>Compression codec</name>
</value>
                            </entry>
                            <entry>
<key>Ignore Locality</key>
<value>
    <name>Ignore Locality</name>
</value>
                            </entry>
                        </descriptors>
                        <executionNode>ALL</executionNode>
                        <lossTolerant>false</lossTolerant>
                        <penaltyDuration>30 sec</penaltyDuration>
                        <properties>
                            <entry>
<key>Hadoop Configuration Resources</key>
<value>/opt/nifi_conf/core-site.xml,/opt/nifi_conf/hdfs-site.xml</value>
                            </entry>
                            <entry>
<key>kerberos-credentials-service</key>
                            </entry>
                            <entry>
<key>kerberos-user-service</key>
                            </entry>
                            <entry>
<key>Kerberos Principal</key>
                            </entry>
                            <entry>
<key>Kerberos Keytab</key>
                            </entry>
                            <entry>
<key>Kerberos Password</key>
                            </entry>
                            <entry>
<key>Kerberos Relogin Period</key>
<value>4 hours</value>
                            </entry>
                            <entry>
<key>Additional Classpath Resources</key>
                            </entry>
                            <entry>
<key>Directory</key>
<value>/home/datalake/swimrankings</value>
                            </entry>
                            <entry>
<key>Conflict Resolution Strategy</key>
<value>append</value>
                            </entry>
                            <entry>
<key>writing-strategy</key>
<value>writeAndRename</value>
                            </entry>
                            <entry>
<key>Block Size</key>
                            </entry>
                            <entry>
<key>IO Buffer Size</key>
                            </entry>
                            <entry>
<key>Replication</key>
                            </entry>
                            <entry>
<key>Permissions umask</key>
                            </entry>
                            <entry>
<key>Remote Owner</key>
                            </entry>
                            <entry>
<key>Remote Group</key>
                            </entry>
                            <entry>
<key>Compression codec</key>
<value>NONE</value>
                            </entry>
                            <entry>
<key>Ignore Locality</key>
<value>false</value>
                            </entry>
                        </properties>
                        <runDurationMillis>0</runDurationMillis>
                        <schedulingPeriod>0 sec</schedulingPeriod>
                        <schedulingStrategy>TIMER_DRIVEN</schedulingStrategy>
                        <yieldDuration>1 sec</yieldDuration>
                    </config>
                    <executionNodeRestricted>false</executionNodeRestricted>
                    <name>grabarEnHDFS</name>
                    <relationships>
                        <autoTerminate>true</autoTerminate>
                        <name>failure</name>
                    </relationships>
                    <relationships>
                        <autoTerminate>false</autoTerminate>
                        <name>success</name>
                    </relationships>
                    <state>RUNNING</state>
                    <style/>
                    <type>org.apache.nifi.processors.hadoop.PutHDFS</type>
                </processors>
            </contents>
            <defaultBackPressureDataSizeThreshold>1 GB</defaultBackPressureDataSizeThreshold>
            <defaultBackPressureObjectThreshold>10000</defaultBackPressureObjectThreshold>
            <defaultFlowFileExpiration>0 sec</defaultFlowFileExpiration>
            <flowfileConcurrency>UNBOUNDED</flowfileConcurrency>
            <flowfileOutboundPolicy>STREAM_WHEN_AVAILABLE</flowfileOutboundPolicy>
            <name>masterClass</name>
            <variables/>
        </processGroups>
    </snippet>
    <timestamp>09/25/2022 21:23:54 UTC</timestamp>
</template>
